{"generatedAtUtc":"2026-04-21T00:00:00Z","sourceCommit":"dev-stub","count":35,"entries":{"KORD":{"i":"KORD","n":"Chicago O'Hare International Airport","c":"Chicago","s":"IL","la":41.97860,"lo":-87.90480,"e":672},"KMDW":{"i":"KMDW","n":"Chicago Midway International Airport","c":"Chicago","s":"IL","la":41.78598,"lo":-87.75242,"e":620},"KDPA":{"i":"KDPA","n":"DuPage Airport","c":"West Chicago","s":"IL","la":41.90778,"lo":-88.24860,"e":759},"KLOT":{"i":"KLOT","n":"Lewis University Airport","c":"Romeoville","s":"IL","la":41.60725,"lo":-88.09618,"e":679},"KJFK":{"i":"KJFK","n":"John F Kennedy International Airport","c":"New York","s":"NY","la":40.63980,"lo":-73.77890,"e":13},"KLGA":{"i":"KLGA","n":"LaGuardia Airport","c":"New York","s":"NY","la":40.77724,"lo":-73.87261,"e":21},"KEWR":{"i":"KEWR","n":"Newark Liberty International Airport","c":"Newark","s":"NJ","la":40.69250,"lo":-74.16867,"e":18},"KLAX":{"i":"KLAX","n":"Los Angeles International Airport","c":"Los Angeles","s":"CA","la":33.94250,"lo":-118.40807,"e":125},"KSFO":{"i":"KSFO","n":"San Francisco International Airport","c":"San Francisco","s":"CA","la":37.61880,"lo":-122.37500,"e":13},"KSJC":{"i":"KSJC","n":"Norman Y. Mineta San Jose International Airport","c":"San Jose","s":"CA","la":37.36260,"lo":-121.92900,"e":62},"KSAN":{"i":"KSAN","n":"San Diego International Airport","c":"San Diego","s":"CA","la":32.73360,"lo":-117.19050,"e":17},"KDEN":{"i":"KDEN","n":"Denver International Airport","c":"Denver","s":"CO","la":39.85841,"lo":-104.66700,"e":5431},"KATL":{"i":"KATL","n":"Hartsfield-Jackson Atlanta International Airport","c":"Atlanta","s":"GA","la":33.63670,"lo":-84.42810,"e":1026},"KSEA":{"i":"KSEA","n":"Seattle-Tacoma International Airport","c":"Seattle","s":"WA","la":47.44898,"lo":-122.30931,"e":433},"KPDX":{"i":"KPDX","n":"Portland International Airport","c":"Portland","s":"OR","la":45.58869,"lo":-122.59750,"e":31},"KBOS":{"i":"KBOS","n":"General Edward Lawrence Logan International Airport","c":"Boston","s":"MA","la":42.36430,"lo":-71.00520,"e":20},"KPHX":{"i":"KPHX","n":"Phoenix Sky Harbor International Airport","c":"Phoenix","s":"AZ","la":33.43430,"lo":-112.01200,"e":1135},"KLAS":{"i":"KLAS","n":"Harry Reid International Airport","c":"Las Vegas","s":"NV","la":36.08010,"lo":-115.15220,"e":2181},"KDFW":{"i":"KDFW","n":"Dallas/Fort Worth International Airport","c":"Dallas-Fort Worth","s":"TX","la":32.89680,"lo":-97.03800,"e":607},"KIAH":{"i":"KIAH","n":"George Bush Intercontinental Houston Airport","c":"Houston","s":"TX","la":29.98440,"lo":-95.34140,"e":97},"KMIA":{"i":"KMIA","n":"Miami International Airport","c":"Miami","s":"FL","la":25.79325,"lo":-80.29060,"e":8},"KBWI":{"i":"KBWI","n":"Baltimore/Washington International Thurgood Marshall Airport","c":"Baltimore","s":"MD","la":39.17540,"lo":-76.66820,"e":146},"KCLT":{"i":"KCLT","n":"Charlotte Douglas International Airport","c":"Charlotte","s":"NC","la":35.21400,"lo":-80.94310,"e":748},"KMSP":{"i":"KMSP","n":"Minneapolis-St Paul International Airport","c":"Minneapolis","s":"MN","la":44.88200,"lo":-93.22180,"e":841},"KDTW":{"i":"KDTW","n":"Detroit Metropolitan Wayne County Airport","c":"Detroit","s":"MI","la":42.21240,"lo":-83.35340,"e":645},"KPHL":{"i":"KPHL","n":"Philadelphia International Airport","c":"Philadelphia","s":"PA","la":39.87190,"lo":-75.24110,"e":36},"KORF":{"i":"KORF","n":"Norfolk International Airport","c":"Norfolk","s":"VA","la":36.89460,"lo":-76.20120,"e":26},"KRIC":{"i":"KRIC","n":"Richmond International Airport","c":"Richmond","s":"VA","la":37.50520,"lo":-77.32050,"e":167},"KIAD":{"i":"KIAD","n":"Washington Dulles International Airport","c":"Washington","s":"DC","la":38.94450,"lo":-77.45580,"e":313},"KDCA":{"i":"KDCA","n":"Ronald Reagan Washington National Airport","c":"Arlington","s":"VA","la":38.85210,"lo":-77.03770,"e":15},"KSLC":{"i":"KSLC","n":"Salt Lake City International Airport","c":"Salt Lake City","s":"UT","la":40.78839,"lo":-111.97770,"e":4227},"KMKE":{"i":"KMKE","n":"General Mitchell International Airport","c":"Milwaukee","s":"WI","la":42.94722,"lo":-87.89658,"e":723},"KCLE":{"i":"KCLE","n":"Cleveland Hopkins International Airport","c":"Cleveland","s":"OH","la":41.41190,"lo":-81.84980,"e":791},"KSTL":{"i":"KSTL","n":"St Louis Lambert International Airport","c":"St Louis","s":"MO","la":38.74690,"lo":-90.35999,"e":618},"KBNA":{"i":"KBNA","n":"Nashville International Airport","c":"Nashville","s":"TN","la":36.12450,"lo":-86.67820,"e":599}}}
